rber474.releaser-1.0a10-py3.12-nspkg.pth
rber474/releaser/utils.py
rber474/releaser/tests/__init__.py
rber474/releaser/towncrier/__init__.py
rber474.releaser-1.0a10.dist-info/LICENSE.GPL
rber474.releaser-1.0a10.dist-info/LICENSE.rst
rber474.releaser-1.0a10.dist-info/METADATA
rber474.releaser-1.0a10.dist-info/WHEEL
rber474.releaser-1.0a10.dist-info/entry_points.txt
rber474.releaser-1.0a10.dist-info/namespace_packages.txt
rber474.releaser-1.0a10.dist-info/top_level.txt
rber474.releaser-1.0a10.dist-info/RECORD
