Metadata-Version: 2.1
Name: rber474.releaser
Version: 1.0a10
Summary: Custom releaser hooks for ONCE project based on zest.releaser
Home-page: https://github.com/rber474/rber474.releaser
Author: Rafael Bermúdez Horcajada
Author-email: rber474@gmail.com
License: GPL version 2
Project-URL: PyPI, https://pypi.org/project/rber474.releaser/
Project-URL: Source, https://github.com/rber474/rber474.releaser
Project-URL: Tracker, https://github.com/rber474/rber474.releaser/issues
Keywords: zest.releaser release upload custom PyPI SCP SFTP package sdist
Classifier: Development Status :: 2 - Pre-Alpha
Classifier: Environment :: Console
Classifier: Environment :: Plugins
Classifier: Intended Audience :: Developers
Classifier: Programming Language :: Python
Classifier: Programming Language :: Python :: 3.9
Classifier: Programming Language :: Python :: 3.10
Classifier: Programming Language :: Python :: 3.11
Classifier: Operating System :: OS Independent
Classifier: License :: OSI Approved :: GNU General Public License v2 (GPLv2)
Classifier: Topic :: Software Development
Classifier: Topic :: Software Development :: Libraries :: Python Modules
Classifier: Topic :: System :: Archiving :: Packaging
Classifier: Topic :: System :: Installation/Setup
Classifier: Topic :: Utilities
Requires-Python: >=3.9
License-File: LICENSE.GPL
License-File: LICENSE.rst
Requires-Dist: setuptools>=68.0.0
Requires-Dist: zest.releaser
Requires-Dist: zestreleaser.towncrier
Requires-Dist: towncrier
Provides-Extra: test
Requires-Dist: wheel; extra == "test"
Requires-Dist: zope.testing; extra == "test"
Requires-Dist: zope.testrunner; extra == "test"
